SourceQueryBot/__init__.py
SourceQueryBot/cached_messaging.py
SourceQueryBot/exceptions.py
SourceQueryBot/messages.py
SourceQueryBot/settings.py
SourceQueryBot/translations.py
SourceQueryBot-1.0.5.dist-info/LICENSE.md
SourceQueryBot-1.0.5.dist-info/METADATA
SourceQueryBot-1.0.5.dist-info/WHEEL
SourceQueryBot-1.0.5.dist-info/top_level.txt
SourceQueryBot-1.0.5.dist-info/RECORD
