Metadata-Version: 2.1
Name: SourceQueryBot
Version: 1.0.5
Summary: Discord server A2S bot.
Home-page: https://github.com/WardPearce/SourceQueryBot
Author: WardPearce
Author-email: wardpearce@protonmail.com
License: GPL v3
Platform: UNKNOWN
Requires-Python: >=3.6
Requires-Dist: aioquery (>=1.1.0)
Requires-Dist: aiofiles (>=0.4.0)
Requires-Dist: discord.py (>=1.1.0)
